generalagent/.DS_Store
generalagent/__init__.py
generalagent/agent/__init__.py
generalagent/agent/abs_agent.py
generalagent/agent/normal_agent.py
generalagent/agent/stack_agent.py
generalagent/cli.py
generalagent/interpreter/__init__.py
generalagent/interpreter/applescript_interpreter.py
generalagent/interpreter/embedding_retrieve_interpreter.py
generalagent/interpreter/file_interpreter.py
generalagent/interpreter/interpreter.py
generalagent/interpreter/link_retrieve_interpreter.py
generalagent/interpreter/plan_interpreter.py
generalagent/interpreter/python_interpreter.py
generalagent/interpreter/role_interpreter.py
generalagent/interpreter/shell_interpreter.py
generalagent/interpreter/ui_interpreter.py
generalagent/memory/__init__.py
generalagent/memory/link_memory.py
generalagent/memory/normal_memory.py
generalagent/memory/stack_memory.py
generalagent/requirements.txt
generalagent/skills/.DS_Store
generalagent/skills/__init__.py
generalagent/skills/ai_draw_prompt_gen.py
generalagent/skills/application_builder.py
generalagent/skills/applications.py
generalagent/skills/build_web.py
generalagent/skills/download_file.py
generalagent/skills/llm_inference.py
generalagent/skills/memory_utils.py
generalagent/skills/python_envs.py
generalagent/skills/read_file_content.py
generalagent/skills/replicate_api.py
generalagent/skills/split_text.py
generalagent/skills/text_is_english.py
generalagent/skills/text_to_speech.py
generalagent/skills/text_translation.py
generalagent/skills/token_count.py
generalagent/skills/unique_name.py
generalagent/skills/web_tools.py
generalagent/utils.py
generalagent-0.0.6.dist-info/LICENSE
generalagent-0.0.6.dist-info/METADATA
generalagent-0.0.6.dist-info/WHEEL
generalagent-0.0.6.dist-info/entry_points.txt
generalagent-0.0.6.dist-info/RECORD
