Metadata-Version: 2.1
Name: GeneralAgent
Version: 0.0.6
Summary: General Agent: From LLM to Agent
Home-page: https://github.com/CosmosShadow/GeneralAgent
License: Apache 2.0
Author: Chen Li
Author-email: lichenarthurdata@gmail.com
Requires-Python: >=3.8,<4.0
Classifier: License :: Other/Proprietary License
Classifier: Programming Language :: Python :: 3
Classifier: Programming Language :: Python :: 3.8
Classifier: Programming Language :: Python :: 3.9
Classifier: Programming Language :: Python :: 3.10
Classifier: Programming Language :: Python :: 3.11
Classifier: Programming Language :: Python :: 3.12
Requires-Dist: beautifulsoup4 (==4.12.2)
Requires-Dist: bs4 (==0.0.1)
Requires-Dist: chromadb (==0.4.17)
Requires-Dist: edge-tts (==6.1.9)
Requires-Dist: fastapi (==0.104.1)
Requires-Dist: httpx (==0.25.1)
Requires-Dist: jinja2 (==3.1.2)
Requires-Dist: numpy (==1.24.4)
Requires-Dist: openai (==0.27.6)
Requires-Dist: playwright (==1.39.0)
Requires-Dist: pulsar-client (==3.3.0)
Requires-Dist: pydub (==0.25.1)
Requires-Dist: pymongo (==4.6.0)
Requires-Dist: pymupdf (==1.23.6)
Requires-Dist: pypdf (==3.17.1)
Requires-Dist: pytest (==7.4.3)
Requires-Dist: pytest-asyncio (==0.21.1)
Requires-Dist: python-docx (==1.1.0)
Requires-Dist: python-dotenv (==1.0.0)
Requires-Dist: python-multipart (==0.0.6)
Requires-Dist: python-pptx (==0.6.23)
Requires-Dist: replicate (==0.18.1)
Requires-Dist: requests (==2.31.0)
Requires-Dist: retrying (==1.3.4)
Requires-Dist: tiktoken (==0.5.1)
Requires-Dist: tinydb (==4.8.0)
Requires-Dist: uvicorn (==0.24.0.post1)
Requires-Dist: websocket-client-py3 (==0.15.0)
Requires-Dist: websockets (==12.0)
Requires-Dist: yfinance (==0.2.31)
Project-URL: Repository, https://github.com/CosmosShadow/GeneralAgent
